redbox/__init__.py
redbox/box.py
redbox/models/__init__.py
redbox/models/attachment.py
redbox/models/mailbox.py
redbox/models/message.py
redbox/query/__init__.py
redbox/query/query.py
redbox/testing.py
redbox/tests/__init__.py
redbox/tests/conftest.py
redbox/tests/examples/INBOX/1.eml
redbox/tests/examples/INBOX/2.eml
redbox/tests/examples/INBOX/flags.json
redbox/tests/examples/MYBOX/1.eml
redbox/tests/examples/MYBOX/2.eml
redbox/tests/examples/MYBOX/flags.json
redbox/tests/examples/to_you.eml
redbox/tests/test_fetch.py
redbox/tests/test_query.py
redbox/tests/test_search.py
redbox/utils/__init__.py
redbox/utils/inspector.py
redbox2-0.2.3.dist-info/LICENSE
redbox2-0.2.3.dist-info/METADATA
redbox2-0.2.3.dist-info/WHEEL
redbox2-0.2.3.dist-info/RECORD
