Metadata-Version: 2.1
Name: redbox2
Version: 0.2.3
Summary: 
Author: asolana
Author-email: asolana@deloitte.es
Requires-Python: >=3.8,<4.0
Classifier: Programming Language :: Python :: 3
Classifier: Programming Language :: Python :: 3.8
Classifier: Programming Language :: Python :: 3.9
Classifier: Programming Language :: Python :: 3.10
Classifier: Programming Language :: Python :: 3.11
Requires-Dist: pydantic (>=2.2.0,<3.0.0)
Requires-Dist: tomli (>=2.0.1,<3.0.0)
